pezzo/client/__init__.py
pezzo/client/classes.py
pezzo/client/client.py
pezzo/config/__init__.py
pezzo/config/config.py
pezzo/openai/__init__.py
pezzo/openai/openai.py
pezzo/requirements.txt
pezzo/scripts/prebuild.py
pezzo/utils/helpers.py
pezzo/utils/interpolate_variables.py
pezzo/version.txt
pezzo-0.1.2.dist-info/LICENSE.md
pezzo-0.1.2.dist-info/METADATA
pezzo-0.1.2.dist-info/WHEEL
pezzo-0.1.2.dist-info/entry_points.txt
pezzo-0.1.2.dist-info/RECORD
